frosch/__init__.py
frosch/activate.py
frosch/config_manager.py
frosch/dt_hooks/__init__.py
frosch/dt_hooks/hook_numpy.py
frosch/dt_hooks/hook_torch.py
frosch/frosch.py
frosch/notifier.py
frosch/parser.py
frosch/style/__init__.py
frosch/style/token/__init__.py
frosch/type_hooks.py
frosch/writer.py
frosch-0.1.9.dist-info/entry_points.txt
frosch-0.1.9.dist-info/LICENSE
frosch-0.1.9.dist-info/WHEEL
frosch-0.1.9.dist-info/METADATA
frosch-0.1.9.dist-info/RECORD
