Metadata-Version: 2.1
Name: frosch
Version: 0.1.9
Summary: Better runtime error messages
Home-page: https://github.com/HallerPatrick/frosch
License: MIT
Author: Patrick Haller
Author-email: patrickhaller40@googlemail.com
Requires-Python: >=3.6,<4.0
Classifier: License :: OSI Approved :: MIT License
Classifier: Programming Language :: Python :: 3
Classifier: Programming Language :: Python :: 3.10
Classifier: Programming Language :: Python :: 3.6
Classifier: Programming Language :: Python :: 3.7
Classifier: Programming Language :: Python :: 3.8
Classifier: Programming Language :: Python :: 3.9
Requires-Dist: Pygments (>=2.7.2,<3.0.0)
Requires-Dist: asttokens (>=2.0.4,<3.0.0)
Requires-Dist: cheap_repr (>=0.4.5,<0.6.0)
Requires-Dist: colorama (>=0.4.4,<0.5.0)
Requires-Dist: stack-data (>=0.1.0,<0.2.0)
Requires-Dist: yapf (>=0.30,<0.32)
Project-URL: Repository, https://github.com/HallerPatrick/frosch
